dbreak_redis.py
dbreak_redis-0.0.1.dist-info/METADATA
dbreak_redis-0.0.1.dist-info/WHEEL
dbreak_redis-0.0.1.dist-info/entry_points.txt
dbreak_redis-0.0.1.dist-info/top_level.txt
dbreak_redis-0.0.1.dist-info/RECORD
