Metadata-Version: 2.1
Name: dbreak-redis
Version: 0.0.1
Summary: Plugin for dbreak to handle Redis connections
Home-page: https://github.com/jrhege/dbreak_redis
Author: Johnathon Hege
License: UNKNOWN
Keywords: development database redis
Platform: UNKNOWN
Classifier: Development Status :: 3 - Alpha
Classifier: Intended Audience :: Developers
Classifier: License :: OSI Approved :: MIT License
Classifier: Programming Language :: Python :: 3.6
Classifier: Programming Language :: Python :: 3.7
Classifier: Programming Language :: Python :: 3.8
Requires-Python: >=3.6
Requires-Dist: dbreak (>=0.0.1)
Requires-Dist: redis (>=3.4.1)
